{
    "Group": "ACTIVATION",
    "Images": [],
    "Name": "CIRCUIT BREAKERS",
    "ProjectName": "ActivationCBs",
    "Side": 0,
    "SortPriority": 114,
    "Spacecraft": 1,
    "Steps": [
        {
            "Program": 1,
            "SetID": 71,
            "Text": null,
            "ToPosID": 4,
            "Type": 1
        },
        {
            "Program": 1,
            "SetID": 68,
            "Text": null,
            "ToPosID": 5,
            "Type": 1
        },
        {
            "Program": 1,
            "SetID": 69,
            "Text": null,
            "ToPosID": 5,
            "Type": 1
        },
        {
            "Program": 1,
            "SetID": 132,
            "Text": null,
            "ToPosID": 1,
            "Type": 2
        },
        {
            "Program": 1,
            "SetID": 100,
            "Text": null,
            "ToPosID": 1,
            "Type": 2
        },
        {
            "Program": 1,
            "SetID": 58,
            "Text": null,
            "ToPosID": 1,
            "Type": 2
        },
        {
            "Program": 1,
            "SetID": 61,
            "Text": null,
            "ToPosID": 2,
            "Type": 2
        },
        {
            "Program": 1,
            "SetID": 89,
            "Text": null,
            "ToPosID": 2,
            "Type": 2
        },
        {
            "Program": 1,
            "SetID": 90,
            "Text": null,
            "ToPosID": 2,
            "Type": 2
        },
        {
            "Program": 1,
            "SetID": 91,
            "Text": null,
            "ToPosID": 2,
            "Type": 2
        },
        {
            "Program": 1,
            "SetID": 92,
            "Text": null,
            "ToPosID": 2,
            "Type": 2
        },
        {
            "Program": 1,
            "SetID": 95,
            "Text": null,
            "ToPosID": 1,
            "Type": 2
        },
        {
            "Program": 1,
            "SetID": 93,
            "Text": null,
            "ToPosID": 2,
            "Type": 2
        },
        {
            "Program": 1,
            "SetID": 94,
            "Text": null,
            "ToPosID": 2,
            "Type": 2
        },
        {
            "Program": 1,
            "SetID": 13,
            "Text": null,
            "ToPosID": 2,
            "Type": 2
        },
        {
            "Program": 1,
            "SetID": 14,
            "Text": null,
            "ToPosID": 2,
            "Type": 2
        },
        {
            "Program": 1,
            "SetID": 15,
            "Text": null,
            "ToPosID": 2,
            "Type": 2
        },
        {
            "Program": 1,
            "SetID": 16,
            "Text": null,
            "ToPosID": 2,
            "Type": 2
        },
        {
            "Program": 1,
            "SetID": 17,
            "Text": null,
            "ToPosID": 2,
            "Type": 2
        },
        {
            "Program": 1,
            "SetID": 97,
            "Text": null,
            "ToPosID": 2,
            "Type": 2
        },
        {
            "Program": 1,
            "SetID": 98,
            "Text": null,
            "ToPosID": 1,
            "Type": 2
        },
        {
            "Program": 1,
            "SetID": 99,
            "Text": null,
            "ToPosID": 1,
            "Type": 2
        },
        {
            "Program": 1,
            "SetID": 100,
            "Text": null,
            "ToPosID": 2,
            "Type": 2
        },
        {
            "Program": 1,
            "SetID": 101,
            "Text": null,
            "ToPosID": 2,
            "Type": 2
        },
        {
            "Program": 1,
            "SetID": 120,
            "Text": null,
            "ToPosID": 2,
            "Type": 2
        },
        {
            "Program": 1,
            "SetID": 119,
            "Text": null,
            "ToPosID": 1,
            "Type": 2
        },
        {
            "Program": 1,
            "SetID": 118,
            "Text": null,
            "ToPosID": 1,
            "Type": 2
        },
        {
            "Program": 1,
            "SetID": 117,
            "Text": null,
            "ToPosID": 1,
            "Type": 2
        },
        {
            "Program": 1,
            "SetID": 116,
            "Text": null,
            "ToPosID": 1,
            "Type": 2
        },
        {
            "Program": 1,
            "SetID": 115,
            "Text": null,
            "ToPosID": 2,
            "Type": 2
        },
        {
            "Program": 1,
            "SetID": 113,
            "Text": null,
            "ToPosID": 2,
            "Type": 2
        },
        {
            "Program": 1,
            "SetID": 114,
            "Text": null,
            "ToPosID": 2,
            "Type": 2
        },
        {
            "Program": 1,
            "SetID": 112,
            "Text": null,
            "ToPosID": 2,
            "Type": 2
        },
        {
            "Program": 1,
            "SetID": 111,
            "Text": null,
            "ToPosID": 2,
            "Type": 2
        },
        {
            "Program": 1,
            "SetID": 110,
            "Text": null,
            "ToPosID": 2,
            "Type": 2
        },
        {
            "Program": 1,
            "SetID": 109,
            "Text": null,
            "ToPosID": 1,
            "Type": 2
        },
        {
            "Program": 1,
            "SetID": 108,
            "Text": null,
            "ToPosID": 2,
            "Type": 2
        },
        {
            "Program": 1,
            "SetID": 107,
            "Text": null,
            "ToPosID": 2,
            "Type": 2
        },
        {
            "Program": 1,
            "SetID": 106,
            "Text": null,
            "ToPosID": 2,
            "Type": 2
        },
        {
            "Program": 1,
            "SetID": 105,
            "Text": null,
            "ToPosID": 2,
            "Type": 2
        },
        {
            "Program": 1,
            "SetID": 104,
            "Text": null,
            "ToPosID": 2,
            "Type": 2
        },
        {
            "Program": 1,
            "SetID": 103,
            "Text": null,
            "ToPosID": 2,
            "Type": 2
        },
        {
            "Program": 1,
            "SetID": 102,
            "Text": null,
            "ToPosID": 2,
            "Type": 2
        },
        {
            "Program": 1,
            "SetID": 121,
            "Text": null,
            "ToPosID": 2,
            "Type": 2
        },
        {
            "Program": 1,
            "SetID": 123,
            "Text": null,
            "ToPosID": 2,
            "Type": 2
        },
        {
            "Program": 1,
            "SetID": 124,
            "Text": null,
            "ToPosID": 2,
            "Type": 2
        },
        {
            "Program": 1,
            "SetID": 126,
            "Text": null,
            "ToPosID": 2,
            "Type": 2
        },
        {
            "Program": 1,
            "SetID": 127,
            "Text": null,
            "ToPosID": 2,
            "Type": 2
        },
        {
            "Program": 1,
            "SetID": 128,
            "Text": null,
            "ToPosID": 1,
            "Type": 2
        },
        {
            "Program": 1,
            "SetID": 129,
            "Text": null,
            "ToPosID": 2,
            "Type": 2
        },
        {
            "Program": 1,
            "SetID": 130,
            "Text": null,
            "ToPosID": 2,
            "Type": 2
        },
        {
            "Program": 1,
            "SetID": 131,
            "Text": null,
            "ToPosID": 1,
            "Type": 2
        },
        {
            "Program": 1,
            "SetID": 132,
            "Text": null,
            "ToPosID": 2,
            "Type": 2
        },
        {
            "Program": 1,
            "SetID": 133,
            "Text": null,
            "ToPosID": 2,
            "Type": 2
        },
        {
            "Program": 1,
            "SetID": 134,
            "Text": null,
            "ToPosID": 2,
            "Type": 2
        },
        {
            "Program": 1,
            "SetID": 135,
            "Text": null,
            "ToPosID": 2,
            "Type": 2
        },
        {
            "Program": 1,
            "SetID": 136,
            "Text": null,
            "ToPosID": 2,
            "Type": 2
        },
        {
            "Program": 1,
            "SetID": 137,
            "Text": null,
            "ToPosID": 2,
            "Type": 2
        },
        {
            "Program": 1,
            "SetID": 138,
            "Text": null,
            "ToPosID": 2,
            "Type": 2
        },
        {
            "Program": 1,
            "SetID": 139,
            "Text": null,
            "ToPosID": 2,
            "Type": 2
        },
        {
            "Program": 1,
            "SetID": 160,
            "Text": null,
            "ToPosID": 2,
            "Type": 2
        },
        {
            "Program": 1,
            "SetID": 159,
            "Text": null,
            "ToPosID": 2,
            "Type": 2
        },
        {
            "Program": 1,
            "SetID": 158,
            "Text": null,
            "ToPosID": 2,
            "Type": 2
        },
        {
            "Program": 1,
            "SetID": 157,
            "Text": null,
            "ToPosID": 2,
            "Type": 2
        },
        {
            "Program": 1,
            "SetID": 156,
            "Text": null,
            "ToPosID": 1,
            "Type": 2
        },
        {
            "Program": 1,
            "SetID": 155,
            "Text": null,
            "ToPosID": 1,
            "Type": 2
        },
        {
            "Program": 1,
            "SetID": 154,
            "Text": null,
            "ToPosID": 2,
            "Type": 2
        },
        {
            "Program": 1,
            "SetID": 153,
            "Text": null,
            "ToPosID": 2,
            "Type": 2
        },
        {
            "Program": 1,
            "SetID": 152,
            "Text": null,
            "ToPosID": 2,
            "Type": 2
        },
        {
            "Program": 1,
            "SetID": 151,
            "Text": null,
            "ToPosID": 2,
            "Type": 2
        },
        {
            "Program": 1,
            "SetID": 150,
            "Text": null,
            "ToPosID": 2,
            "Type": 2
        },
        {
            "Program": 1,
            "SetID": 149,
            "Text": null,
            "ToPosID": 2,
            "Type": 2
        },
        {
            "Program": 1,
            "SetID": 148,
            "Text": null,
            "ToPosID": 2,
            "Type": 2
        },
        {
            "Program": 1,
            "SetID": 147,
            "Text": null,
            "ToPosID": 2,
            "Type": 2
        },
        {
            "Program": 1,
            "SetID": 146,
            "Text": null,
            "ToPosID": 1,
            "Type": 2
        },
        {
            "Program": 1,
            "SetID": 145,
            "Text": null,
            "ToPosID": 2,
            "Type": 2
        },
        {
            "Program": 1,
            "SetID": 144,
            "Text": null,
            "ToPosID": 1,
            "Type": 2
        },
        {
            "Program": 1,
            "SetID": 143,
            "Text": null,
            "ToPosID": 1,
            "Type": 2
        },
        {
            "Program": 1,
            "SetID": 142,
            "Text": null,
            "ToPosID": 2,
            "Type": 2
        },
        {
            "Program": 1,
            "SetID": 141,
            "Text": null,
            "ToPosID": 2,
            "Type": 2
        },
        {
            "Program": 1,
            "SetID": 140,
            "Text": null,
            "ToPosID": 1,
            "Type": 2
        },
        {
            "Program": 1,
            "SetID": 18,
            "Text": null,
            "ToPosID": 2,
            "Type": 2
        },
        {
            "Program": 1,
            "SetID": 19,
            "Text": null,
            "ToPosID": 2,
            "Type": 2
        },
        {
            "Program": 1,
            "SetID": 20,
            "Text": null,
            "ToPosID": 2,
            "Type": 2
        },
        {
            "Program": 1,
            "SetID": 21,
            "Text": null,
            "ToPosID": 1,
            "Type": 2
        },
        {
            "Program": 1,
            "SetID": 22,
            "Text": null,
            "ToPosID": 2,
            "Type": 2
        },
        {
            "Program": 1,
            "SetID": 23,
            "Text": null,
            "ToPosID": 2,
            "Type": 2
        },
        {
            "Program": 1,
            "SetID": 24,
            "Text": null,
            "ToPosID": 2,
            "Type": 2
        },
        {
            "Program": 1,
            "SetID": 25,
            "Text": null,
            "ToPosID": 1,
            "Type": 2
        },
        {
            "Program": 1,
            "SetID": 26,
            "Text": null,
            "ToPosID": 2,
            "Type": 2
        },
        {
            "Program": 1,
            "SetID": 27,
            "Text": null,
            "ToPosID": 1,
            "Type": 2
        },
        {
            "Program": 1,
            "SetID": 28,
            "Text": null,
            "ToPosID": 2,
            "Type": 2
        },
        {
            "Program": 1,
            "SetID": 109,
            "Text": null,
            "ToPosID": 2,
            "Type": 2
        },
        {
            "Program": 1,
            "SetID": 36,
            "Text": null,
            "ToPosID": 2,
            "Type": 2
        },
        {
            "Program": 1,
            "SetID": 37,
            "Text": null,
            "ToPosID": 2,
            "Type": 2
        },
        {
            "Program": 1,
            "SetID": 36,
            "Text": null,
            "ToPosID": 2,
            "Type": 2
        },
        {
            "Program": 1,
            "SetID": 38,
            "Text": null,
            "ToPosID": 2,
            "Type": 2
        },
        {
            "Program": 1,
            "SetID": 39,
            "Text": null,
            "ToPosID": 2,
            "Type": 2
        },
        {
            "Program": 1,
            "SetID": 40,
            "Text": null,
            "ToPosID": 2,
            "Type": 2
        },
        {
            "Program": 1,
            "SetID": 41,
            "Text": null,
            "ToPosID": 2,
            "Type": 2
        },
        {
            "Program": 1,
            "SetID": 42,
            "Text": null,
            "ToPosID": 2,
            "Type": 2
        },
        {
            "Program": 1,
            "SetID": 43,
            "Text": null,
            "ToPosID": 1,
            "Type": 2
        },
        {
            "Program": 1,
            "SetID": 44,
            "Text": null,
            "ToPosID": 1,
            "Type": 2
        },
        {
            "Program": 1,
            "SetID": 45,
            "Text": null,
            "ToPosID": 1,
            "Type": 2
        },
        {
            "Program": 1,
            "SetID": 46,
            "Text": null,
            "ToPosID": 1,
            "Type": 2
        },
        {
            "Program": 1,
            "SetID": 47,
            "Text": null,
            "ToPosID": 2,
            "Type": 2
        },
        {
            "Program": 1,
            "SetID": 48,
            "Text": null,
            "ToPosID": 2,
            "Type": 2
        },
        {
            "Program": 1,
            "SetID": 49,
            "Text": null,
            "ToPosID": 2,
            "Type": 2
        },
        {
            "Program": 1,
            "SetID": 50,
            "Text": null,
            "ToPosID": 2,
            "Type": 2
        },
        {
            "Program": 1,
            "SetID": 51,
            "Text": null,
            "ToPosID": 2,
            "Type": 2
        },
        {
            "Program": 1,
            "SetID": 69,
            "Text": null,
            "ToPosID": 2,
            "Type": 2
        },
        {
            "Program": 1,
            "SetID": 68,
            "Text": null,
            "ToPosID": 2,
            "Type": 2
        },
        {
            "Program": 1,
            "SetID": 67,
            "Text": null,
            "ToPosID": 2,
            "Type": 2
        },
        {
            "Program": 1,
            "SetID": 66,
            "Text": null,
            "ToPosID": 2,
            "Type": 2
        },
        {
            "Program": 1,
            "SetID": 65,
            "Text": null,
            "ToPosID": 2,
            "Type": 2
        },
        {
            "Program": 1,
            "SetID": 64,
            "Text": null,
            "ToPosID": 2,
            "Type": 2
        },
        {
            "Program": 1,
            "SetID": 63,
            "Text": null,
            "ToPosID": 2,
            "Type": 2
        },
        {
            "Program": 1,
            "SetID": 62,
            "Text": null,
            "ToPosID": 2,
            "Type": 2
        },
        {
            "Program": 1,
            "SetID": 61,
            "Text": null,
            "ToPosID": 2,
            "Type": 2
        },
        {
            "Program": 1,
            "SetID": 60,
            "Text": null,
            "ToPosID": 1,
            "Type": 2
        },
        {
            "Program": 1,
            "SetID": 59,
            "Text": null,
            "ToPosID": 2,
            "Type": 2
        },
        {
            "Program": 1,
            "SetID": 58,
            "Text": null,
            "ToPosID": 1,
            "Type": 2
        },
        {
            "Program": 1,
            "SetID": 57,
            "Text": null,
            "ToPosID": 1,
            "Type": 2
        },
        {
            "Program": 1,
            "SetID": 56,
            "Text": null,
            "ToPosID": 2,
            "Type": 2
        },
        {
            "Program": 1,
            "SetID": 55,
            "Text": null,
            "ToPosID": 1,
            "Type": 2
        },
        {
            "Program": 1,
            "SetID": 54,
            "Text": null,
            "ToPosID": 2,
            "Type": 2
        },
        {
            "Program": 1,
            "SetID": 53,
            "Text": null,
            "ToPosID": 2,
            "Type": 2
        },
        {
            "Program": 1,
            "SetID": 52,
            "Text": null,
            "ToPosID": 2,
            "Type": 2
        },
        {
            "Program": 1,
            "SetID": 70,
            "Text": null,
            "ToPosID": 2,
            "Type": 2
        },
        {
            "Program": 1,
            "SetID": 71,
            "Text": null,
            "ToPosID": 2,
            "Type": 2
        },
        {
            "Program": 1,
            "SetID": 77,
            "Text": null,
            "ToPosID": 2,
            "Type": 2
        },
        {
            "Program": 1,
            "SetID": 78,
            "Text": null,
            "ToPosID": 2,
            "Type": 2
        },
        {
            "Program": 1,
            "SetID": 72,
            "Text": null,
            "ToPosID": 2,
            "Type": 2
        },
        {
            "Program": 1,
            "SetID": 73,
            "Text": null,
            "ToPosID": 2,
            "Type": 2
        },
        {
            "Program": 1,
            "SetID": 75,
            "Text": null,
            "ToPosID": 1,
            "Type": 2
        },
        {
            "Program": 1,
            "SetID": 76,
            "Text": null,
            "ToPosID": 2,
            "Type": 2
        },
        {
            "Program": 1,
            "SetID": 79,
            "Text": null,
            "ToPosID": 1,
            "Type": 2
        },
        {
            "Program": 1,
            "SetID": 80,
            "Text": null,
            "ToPosID": 2,
            "Type": 2
        },
        {
            "Program": 1,
            "SetID": 81,
            "Text": null,
            "ToPosID": 1,
            "Type": 2
        },
        {
            "Program": 1,
            "SetID": 82,
            "Text": null,
            "ToPosID": 2,
            "Type": 2
        },
        {
            "Program": 1,
            "SetID": 83,
            "Text": null,
            "ToPosID": 2,
            "Type": 2
        },
        {
            "Program": 1,
            "SetID": 84,
            "Text": null,
            "ToPosID": 2,
            "Type": 2
        },
        {
            "Program": 1,
            "SetID": 85,
            "Text": null,
            "ToPosID": 2,
            "Type": 2
        },
        {
            "Program": 1,
            "SetID": 86,
            "Text": null,
            "ToPosID": 1,
            "Type": 2
        },
        {
            "Program": 1,
            "SetID": 87,
            "Text": null,
            "ToPosID": 2,
            "Type": 2
        },
        {
            "Program": 1,
            "SetID": 1,
            "Text": null,
            "ToPosID": 2,
            "Type": 2
        },
        {
            "Program": 1,
            "SetID": 2,
            "Text": null,
            "ToPosID": 2,
            "Type": 2
        },
        {
            "Program": 1,
            "SetID": 3,
            "Text": null,
            "ToPosID": 1,
            "Type": 2
        },
        {
            "Program": 1,
            "SetID": 4,
            "Text": null,
            "ToPosID": 1,
            "Type": 2
        },
        {
            "Program": 1,
            "SetID": 5,
            "Text": null,
            "ToPosID": 2,
            "Type": 2
        },
        {
            "Program": 1,
            "SetID": 6,
            "Text": null,
            "ToPosID": 2,
            "Type": 2
        },
        {
            "Program": 1,
            "SetID": 7,
            "Text": null,
            "ToPosID": 2,
            "Type": 2
        },
        {
            "Program": 1,
            "SetID": 8,
            "Text": null,
            "ToPosID": 1,
            "Type": 2
        },
        {
            "Program": 1,
            "SetID": 9,
            "Text": null,
            "ToPosID": 2,
            "Type": 2
        },
        {
            "Program": 1,
            "SetID": 10,
            "Text": null,
            "ToPosID": 2,
            "Type": 2
        },
        {
            "Program": 1,
            "SetID": 11,
            "Text": null,
            "ToPosID": 2,
            "Type": 2
        },
        {
            "Program": 1,
            "SetID": 12,
            "Text": null,
            "ToPosID": 2,
            "Type": 2
        },
        {
            "Program": 1,
            "SetID": 33,
            "Text": null,
            "ToPosID": 1,
            "Type": 2
        },
        {
            "Program": 1,
            "SetID": 34,
            "Text": null,
            "ToPosID": 2,
            "Type": 2
        },
        {
            "Program": 1,
            "SetID": 35,
            "Text": null,
            "ToPosID": 2,
            "Type": 2
        },
        {
            "Program": 1,
            "SetID": 32,
            "Text": null,
            "ToPosID": 2,
            "Type": 2
        },
        {
            "Program": 1,
            "SetID": 31,
            "Text": null,
            "ToPosID": 2,
            "Type": 2
        },
        {
            "Program": 1,
            "SetID": 30,
            "Text": null,
            "ToPosID": 2,
            "Type": 2
        },
        {
            "Program": 1,
            "SetID": 29,
            "Text": null,
            "ToPosID": 2,
            "Type": 2
        },
        {
            "Program": 1,
            "SetID": 0,
            "Text": "Check the Master Alarm checks according to the Checklist (8.)",
            "ToPosID": 0,
            "Type": 0
        },
        {
            "Program": 1,
            "SetID": 60,
            "Text": null,
            "ToPosID": 1,
            "Type": 2
        }
    ],
    "checklistText": "<size=21>CIRCUIT BREAKER ACTIVATION</size>\r\n\r\n1.\r\nPANEL 1:\r\n\tX pointer ind pwr fail lt - on\r\n\tTHRUST ind pwr fail lt - on\r\n\tMPS:\tPRESS ind pwr fail - on\r\n\r\nPANEL 2:\t\r\n\tRCS:\r\n\t\tPRESS ind pwr fail lt - on\r\n\t\tQUANTITY ind pwr fail lt - on\r\n\tX pointer ind pwr fail lt - on\r\nPANEL 1,2:\r\n\tFDAI pwr (tb) - OFF (in view) (not yet implemented)\r\n\r\n\r\n2. Enable ATCA\r\n\r\n\t\t\tCAUTION\r\n\t\tBefore closing CB S/C: ATCA, ensure:\r\n\t\tP01: GUID CONT sw - PNGS\r\n\t\tP03: S/C PGNS & AGS sw - OFF\r\n\r\nPANEL 11:\r\n\tCB S/C: ENG CONT - open\r\n\tCB A/C BUS A: DECA GMBL - open\r\nPANEL 16:\r\n\tCB S/C:\r\n\t\tENG ARM - open\r\n\t\tATCA - close\r\n\r\n3.\r\nPANEL 11:\r\n\tAll cb's - closed, except:\r\n\tCB/AC BUS B:\r\n\t\tSE WIND HTR - as required\r\n\t\tAOT LAMP - open\r\n\tCB/AC BUS A:\r\n\t\tCDR WIND HTR - as required\r\n\t\tAOT LAMP - open\r\n\t\tRNDZ RDR - open\r\n\tCB RCS SYS A:\r\n\t\tQUAD 4, 3, 2, & 1 TCA - open\r\n\r\n\t\t\t\tCAUTION\r\n\t\t\tCB/AC BUS A: RNG/RNG RT must be closed\r\n\t\t\tbefore CB FLT DISTP: RNG/RNG RT\r\n\r\n\tCB FLT DISP: RNG/RNG RT - open\r\n\tCB HTR:\r\n\t\tURINE LINE - as required\r\n\t\tRNDZ RDR STBY - open (required)\r\n\t\tDOCK WINDOW - as required\r\n\tCB S/C:\r\n\t\tAEA - open\r\n\t\tAELD - open\r\n\tCB ECS:\r\n\t\tSUIT FAN 1 - open\r\n\t\tCABIN FAN - open\r\n\tCB COMM:\tCDR AUDIO - open\r\n\tCB PGNS:\r\n\t\tLDG RDR - open\r\n\t\tRNDZ RDR - open\r\n\r\nPANEL 1:\tRNG/ALT ind pwr/sig fail lt - on\r\n\tLGC warn lt - on (up to 20 sec)\r\n\r\nPANEL 11:\r\n\tCB PGNS:\tIMU OPR - open\r\n\tCB EPS:\r\n\t\tCROSS TIE BUS - open\r\n\t\tASC ECA CONT - open\r\n\t\tINV 1 - open\r\nPANEL 1,2:\r\n\tFDAI pwr tb (2) - OFF (in view)\r\n\r\n4.\r\nPANEL 11:\r\n\tCB FLT DISP: ENG/RNG RT - close\r\n\tVerify cb status\r\n\r\n5.\r\nPANEL 8:\r\n\tDES PROPUL:\r\n\t\tFUEL VENT tb - gray\r\n\t\tOXID VENT tb - gray\r\n\tED: LDG GEAR DEPLOY tb - bp\r\n\r\n6.\r\nPANEL 1:\r\n\tTHRUST ind pwr fail lt - off\r\n\tX pointer pwr fail lt - off\r\n\tFDAI pwr tb - on (out of view)\r\n\r\n7,\r\nPANEL 16:\r\n\tAll cb's - closed, except:\r\n\tCB RCS SYS B: QUAD 1, 2, 3, & 4 TCA - open\r\n\tCB LTG: MASTER ALARM - open\r\n\tCB S/C:\r\n\t\tAEA - open\r\n\t\tENG ARM - open\r\n\t\tAELD - open\r\n\tCB COMM:\r\n\t\tSE AUDIO - open\r\n\t\tS BD ANT - open\r\n\t\tTV - open\r\n\tCB ECS:\r\n\t\tGLYCOL PUMP SEC - open\r\n\t\tLGC PUMP - as required\r\n\tCB CAMR: SEQ - open\r\n\tCB EPS:\r\n\t\tASC ECA CONT - open\r\n\t\tCROSS TIE BUS - open\r\n\t\tCROSS TIE BAL LOADS - open\r\n\tVerify cb status\r\n\r\n8.\r\nPANEL 16:\tCB INST: CWEA - open\r\nPANEL 1,2:\tMASTER ALARM - on\r\nPANEL 2:\tC/W PWR caut lt - on\r\nPANEL 16:\tCB INST: CWEA - close\r\nPANEL 1,2:\tMASTER ALARM pb/lt: push/reset\r\nPANEL 1:\tCES AC warn lt - off\r\n\tCES DC warn lt - off\r\nPANEL 2:\tPRE AMPS caut lt - off\r\n\tC/W PWR caut lt - off\r\nPANEL 16:\tCB S/C: AELD - open\r\n\r\n9.\r\nPANEL 1:\r\n\tMPS: PRESS ind pwr fail lt - off\r\n\tASC He REG 1 tb - gray\r\n\tASC He REG 2 tb - gray\r\n\tDES He REG 1 tb - gray\r\n\tDES He REG 2 tb - bp\r\n\r\n10.\r\nPANEL 2:\r\n\tRCS:\r\n\t\tPRESS ind pwr fail lt - off\r\n\t\tQUANTITY ind pwr fail lt - off\r\n\t\tSYS A ASC FUEL tb - bp\r\n\t\tSYS A ASC OXID tb - bp\r\n\t\tSYS B ASC FUEL tb - bp\r\n\t\tSYS B ASC OXID tb - bp\r\n\t\tSYS A QUAD 1, 4, 2, & 3 tb - gray\r\n\t\tSYS B QUAD 1, 4, 2, & 3 tb - gray\r\n\t\tSYS A & B MAIN SOV tb - bp\r\n\t\tCRSFD tv - bp\r\n\tX pointer ind pwr fail lt - off\r\n\tFDAI pwr tb - on (out of view)\r\n\r\n"
}